{
  "date": "2025-11-10",
  "platform": "gp",
  "country": "TW",
  "chart": "top_free",
  "type_counts": {
    "角色扮演": 23,
    "益智": 42,
    "策略": 18,
    "休闲": 40,
    "冒险": 9,
    "体育": 2,
    "模拟": 20,
    "文字": 6,
    "动作": 11,
    "桌面和棋类": 4,
    "音乐": 7,
    "卡牌": 4,
    "街机": 6,
    "赌场": 8
  },
  "rows": [
    {
      "rank": 1,
      "app_id": "com.nexon.ma",
      "app_name": "楓之谷：放置冒險記",
      "app_name_zh": "楓之谷：放置冒險記",
      "developer": "NEXON Company",
      "genre": "角色扮演",
      "delta": 0,
      "alert": false,
      "ai_type": "其他"
    },
    {
      "rank": 2,
      "app_id": "com.rastargame.rrygl.tw",
      "app_name": "人人有功練：腸仔江湖見",
      "app_name_zh": "人人有功練：腸仔江湖見",
      "developer": "RASTAR GAMES HK",
      "genre": "角色扮演",
      "delta": 0,
      "alert": false,
      "ai_type": "其他"
    },
    {
      "rank": 3,
      "app_id": "com.swordbh.gp",
      "app_name": "熱血江湖：福利加強版",
      "app_name_zh": "熱血江湖：福利加強版",
      "developer": "Star Entertainment HK",
      "genre": "角色扮演",
      "delta": 0,
      "alert": false,
      "ai_type": "其他"
    },
    {
      "rank": 4,
      "app_id": "com.xyft.az",
      "app_name": "開天 - 林志穎代言",
      "app_name_zh": "開天 - 林志穎代言",
      "developer": "Rays Network Limited",
      "genre": "角色扮演",
      "delta": 0,
      "alert": false,
      "ai_type": "其他"
    },
    {
      "rank": 5,
      "app_id": "com.block.juggle",
      "app_name": "Block Blast!",
      "app_name_zh": "Block Blast!",
      "developer": "HungryStudio",
      "genre": "益智",
      "delta": -1,
      "alert": false,
      "ai_type": "休閒益智"
    },
    {
      "rank": 6,
      "app_id": "com.yzlmcbt.tw.and",
      "app_name": "勇者來開團CBT",
      "app_name_zh": "勇者來開團CBT",
      "developer": "Joy Nice Games",
      "genre": "角色扮演",
      "delta": 0,
      "alert": false,
      "ai_type": "其他"
    },
    {
      "rank": 7,
      "app_id": "com.blueplanetm.gp",
      "app_name": "蔚藍星球: 國王很忙",
      "app_name_zh": "蔚藍星球: 國王很忙",
      "developer": "Shiyue Network",
      "genre": "策略",
      "delta": -4,
      "alert": false,
      "ai_type": "策略對戰"
    },
    {
      "rank": 8,
      "app_id": "com.red.sortingstore.android",
      "app_name": "Water Match™- ASMR Water Sort",
      "app_name_zh": "Water Match™- ASMR Water Sort",
      "developer": "TAP GAMES",
      "genre": "休闲",
      "delta": 17,
      "alert": false,
      "ai_type": "休閒益智"
    },
    {
      "rank": 9,
      "app_id": "com.nianticlabs.pikmin",
      "app_name": "Pikmin Bloom",
      "app_name_zh": "Pikmin Bloom",
      "developer": "Niantic, Inc.",
      "genre": "冒险",
      "delta": 23,
      "alert": false,
      "ai_type": "其他"
    },
    {
      "rank": 10,
      "app_id": "com.qs.jshnh",
      "app_name": "姐是好女孩：二狗的逆襲",
      "app_name_zh": "姐是好女孩：二狗的逆襲",
      "developer": "QinsGames",
      "genre": "休闲",
      "delta": 68,
      "alert": false,
      "ai_type": "休閒益智"
    },
    {
      "rank": 11,
      "app_id": "com.smilegate.chaoszero.stove.google",
      "app_name": "卡厄思夢境",
      "app_name_zh": "卡厄思夢境",
      "developer": "Smilegate Holdings, Inc",
      "genre": "角色扮演",
      "delta": -6,
      "alert": false,
      "ai_type": "角色扮演"
    },
    {
      "rank": 12,
      "app_id": "com.qs.bptq",
      "app_name": "八零找茬",
      "app_name_zh": "八零找茬",
      "developer": "QinsGames",
      "genre": "休闲",
      "delta": -4,
      "alert": false,
      "ai_type": "休閒益智"
    },
    {
      "rank": 13,
      "app_id": "com.wildcaly.b5.hmt",
      "app_name": "NBA巔峰對決",
      "app_name_zh": "NBA巔峰對決",
      "developer": "Wild Caly PTE. LTD.",
      "genre": "体育",
      "delta": -12,
      "alert": false,
      "ai_type": "動作競技"
    },
    {
      "rank": 14,
      "app_id": "com.floralgames.hjxp",
      "app_name": "我的花園世界 - 真的收到花！",
      "app_name_zh": "我的花園世界 - 真的收到花！",
      "developer": "FLORAL GAMES LIMITED",
      "genre": "休闲",
      "delta": -5,
      "alert": false,
      "ai_type": "休閒益智"
    },
    {
      "rank": 15,
      "app_id": "com.roblox.client",
      "app_name": "Roblox",
      "app_name_zh": "Roblox",
      "developer": "Roblox Corporation",
      "genre": "冒险",
      "delta": -4,
      "alert": false,
      "ai_type": "角色扮演"
    },
    {
      "rank": 16,
      "app_id": "com.run.tower.defense",
      "app_name": "Kingshot",
      "app_name_zh": "Kingshot",
      "developer": "Century Games PTE. LTD.",
      "genre": "策略",
      "delta": 0,
      "alert": false,
      "ai_type": "策略對戰"
    },
    {
      "rank": 17,
      "app_id": "com.xman.tw.gp",
      "app_name": "超能戰爭",
      "app_name_zh": "超能戰爭",
      "developer": "Glaciers Game",
      "genre": "休闲",
      "delta": -11,
      "alert": false,
      "ai_type": "休閒益智"
    },
    {
      "rank": 18,
      "app_id": "com.gamincat.jigsolitaire",
      "app_name": "拼圖接龍",
      "app_name_zh": "拼圖接龍",
      "developer": "Gamincat",
      "genre": "益智",
      "delta": -11,
      "alert": false,
      "ai_type": "休閒益智"
    },
    {
      "rank": 19,
      "app_id": "com.ggv.journey.aos",
      "app_name": "RO仙境傳說：米德加茲戰記",
      "app_name_zh": "RO仙境傳說：米德加茲戰記",
      "developer": "Gravity Game Vision",
      "genre": "角色扮演",
      "delta": 0,
      "alert": false,
      "ai_type": "其他"
    },
    {
      "rank": 20,
      "app_id": "com.monster.city.gp",
      "app_name": "怪獸大都市",
      "app_name_zh": "怪獸大都市",
      "developer": "Grid games",
      "genre": "模拟",
      "delta": 0,
      "alert": false,
      "ai_type": "其他"
    },
    {
      "rank": 21,
      "app_id": "com.readygo.barrel.gp",
      "app_name": "Last Z：Survival Shooter（倖存者逃亡）",
      "app_name_zh": "Last Z：Survival Shooter（倖存者逃亡）",
      "developer": "Florere Game",
      "genre": "策略",
      "delta": -7,
      "alert": false,
      "ai_type": "策略對戰"
    },
    {
      "rank": 22,
      "app_id": "associations.connect.words.match.puzzle",
      "app_name": "腦洞大爆炸",
      "app_name_zh": "腦洞大爆炸",
      "developer": "BitEpoch",
      "genre": "文字",
      "delta": -3,
      "alert": false,
      "ai_type": "休閒益智"
    },
    {
      "rank": 23,
      "app_id": "grill.sort.food.games.match.puzzle",
      "app_name": "Grill Sort - 燒烤遊戲，三消遊戲，模擬餐廳遊戲",
      "app_name_zh": "Grill Sort - 燒烤遊戲，三消遊戲，模擬餐廳遊戲",
      "developer": "Gloryway Puzzle Hub",
      "genre": "益智",
      "delta": -8,
      "alert": false,
      "ai_type": "休閒益智"
    },
    {
      "rank": 24,
      "app_id": "com.garena.game.df",
      "app_name": "Garena® 三角洲行動",
      "app_name_zh": "Garena® 三角洲行動",
      "developer": "Garena Mobile Private Limited",
      "genre": "动作",
      "delta": -4,
      "alert": false,
      "ai_type": "動作競技"
    },
    {
      "rank": 25,
      "app_id": "com.bbgame.sanguo.gp.tw",
      "app_name": "三國志:王戰",
      "app_name_zh": "三國志:王戰",
      "developer": "HKBBGL",
      "genre": "策略",
      "delta": -12,
      "alert": false,
      "ai_type": "策略對戰"
    },
    {
      "rank": 26,
      "app_id": "com.lmsg.twgp",
      "app_name": "胸懷三國：美人計",
      "app_name_zh": "胸懷三國：美人計",
      "developer": "Gaia Games Technology Limited",
      "genre": "冒险",
      "delta": -24,
      "alert": false,
      "ai_type": "角色扮演"
    },
    {
      "rank": 27,
      "app_id": "com.fun.lastwar.gp",
      "app_name": "最後的戰爭 - Last War",
      "app_name_zh": "最後的戰爭 - Last War",
      "developer": "FUNFLY PTE. LTD.",
      "genre": "策略",
      "delta": -9,
      "alert": false,
      "ai_type": "策略對戰"
    },
    {
      "rank": 28,
      "app_id": "com.dreamgames.royalkingdom",
      "app_name": "Royal Kingdom",
      "app_name_zh": "Royal Kingdom",
      "developer": "Dream Games, Ltd.",
      "genre": "益智",
      "delta": -2,
      "alert": false,
      "ai_type": "休閒益智"
    },
    {
      "rank": 29,
      "app_id": "com.garena.game.kgtw",
      "app_name": "Garena 傳說對決 X 關於我轉生變成史萊姆這檔事",
      "app_name_zh": "Garena 傳說對決 X 關於我轉生變成史萊姆這檔事",
      "developer": "Garena Games Online",
      "genre": "动作",
      "delta": 0,
      "alert": false,
      "ai_type": "動作競技"
    },
    {
      "rank": 30,
      "app_id": "com.rovio.baba",
      "app_name": "Angry Birds 2",
      "app_name_zh": "Angry Birds 2",
      "developer": "Rovio Entertainment Oy",
      "genre": "休闲",
      "delta": 0,
      "alert": false,
      "ai_type": "休閒益智"
    },
    {
      "rank": 31,
      "app_id": "com.loomgames.pixelflow",
      "app_name": "Pixel Flow!",
      "app_name_zh": "Pixel Flow!",
      "developer": "Loom Games A.Ş.",
      "genre": "益智",
      "delta": 0,
      "alert": false,
      "ai_type": "休閒益智"
    },
    {
      "rank": 32,
      "app_id": "com.furywing.rxzggo.free",
      "app_name": "熱血主公Go! - 三國肉鴿RPG手遊",
      "app_name_zh": "熱血主公Go! - 三國肉鴿RPG手遊",
      "developer": "FW Game Studio",
      "genre": "冒险",
      "delta": 0,
      "alert": false,
      "ai_type": "其他"
    },
    {
      "rank": 33,
      "app_id": "com.abi.skewer.sort",
      "app_name": "Foodie Sizzle: 美食滋滋",
      "app_name_zh": "Foodie Sizzle: 美食滋滋",
      "developer": "ABI GAME",
      "genre": "益智",
      "delta": -10,
      "alert": false,
      "ai_type": "休閒益智"
    },
    {
      "rank": 34,
      "app_id": "com.slg.savagesurvival",
      "app_name": "野蠻生存錄:侏羅紀",
      "app_name_zh": "野蠻生存錄:侏羅紀",
      "developer": "YOTTA GAMES",
      "genre": "策略",
      "delta": 1,
      "alert": false,
      "ai_type": "策略對戰"
    },
    {
      "rank": 35,
      "app_id": "com.gof.global",
      "app_name": "寒霜啟示錄",
      "app_name_zh": "寒霜啟示錄",
      "developer": "Century Games PTE. LTD.",
      "genre": "策略",
      "delta": -11,
      "alert": false,
      "ai_type": "策略對戰"
    },
    {
      "rank": 36,
      "app_id": "defense.roguelike.cell.shoot.survivor",
      "app_name": "細胞保衛戰",
      "app_name_zh": "細胞保衛戰",
      "developer": "Yelo Hood",
      "genre": "角色扮演",
      "delta": -5,
      "alert": false,
      "ai_type": "角色扮演"
    },
    {
      "rank": 37,
      "app_id": "com.fun.brain.game",
      "app_name": "Brain Puzzle: Tricky Quest",
      "app_name_zh": "Brain Puzzle: Tricky Quest",
      "developer": "JoyGame Studio",
      "genre": "益智",
      "delta": 2,
      "alert": false,
      "ai_type": "休閒益智"
    },
    {
      "rank": 38,
      "app_id": "com.cat.hole.puzzle.aos",
      "app_name": "貓咪掉下去",
      "app_name_zh": "貓咪掉下去",
      "developer": "ACTIONFIT",
      "genre": "休闲",
      "delta": 12,
      "alert": false,
      "ai_type": "休閒益智"
    },
    {
      "rank": 39,
      "app_id": "com.wood.block.sudoku.puzzle.bm",
      "app_name": "Block Crush!",
      "app_name_zh": "Block Crush!",
      "developer": "Wonderful  Studio",
      "genre": "益智",
      "delta": -3,
      "alert": false,
      "ai_type": "休閒益智"
    },
    {
      "rank": 40,
      "app_id": "com.ecffri.arrows",
      "app_name": "Arrows – Puzzle Escape",
      "app_name_zh": "Arrows – Puzzle Escape",
      "developer": "Lessmore UG",
      "genre": "益智",
      "delta": 32,
      "alert": false,
      "ai_type": "休閒益智"
    },
    {
      "rank": 41,
      "app_id": "com.vitastudio.mahjong",
      "app_name": "Vita 麻將",
      "app_name_zh": "Vita 麻將",
      "developer": "Vita Studio.",
      "genre": "桌面和棋类",
      "delta": 2,
      "alert": false,
      "ai_type": "社交賭場"
    },
    {
      "rank": 42,
      "app_id": "com.tricky.story.brain.quest",
      "app_name": "Tricky Story",
      "app_name_zh": "Tricky Story",
      "developer": "XGame Global",
      "genre": "益智",
      "delta": 0,
      "alert": false,
      "ai_type": "其他"
    },
    {
      "rank": 43,
      "app_id": "org.gg.crazy.brain",
      "app_name": "瘋狂大腦洞",
      "app_name_zh": "瘋狂大腦洞",
      "developer": "Hainan Play Hi Cultural Entertainment Co., Ltd",
      "genre": "休闲",
      "delta": -21,
      "alert": false,
      "ai_type": "休閒益智"
    },
    {
      "rank": 44,
      "app_id": "surf.beats.magic.song.game",
      "app_name": "我的歌唱寵物：流行鋼琴遊戲",
      "app_name_zh": "我的歌唱寵物：流行鋼琴遊戲",
      "developer": "PulseBeat Studios",
      "genre": "音乐",
      "delta": 139,
      "alert": false,
      "ai_type": "其他"
    },
    {
      "rank": 45,
      "app_id": "com.oakever.tiletrip",
      "app_name": "Tile Explorer - Triple Match",
      "app_name_zh": "Tile Explorer - Triple Match",
      "developer": "Oakever Games",
      "genre": "益智",
      "delta": -12,
      "alert": false,
      "ai_type": "休閒益智"
    },
    {
      "rank": 46,
      "app_id": "com.screw3d.match.nuts.bolts.pin.jam.away.puzzle",
      "app_name": "3D螺絲大師：螺絲消消樂遊戲",
      "app_name_zh": "3D螺絲大師：螺絲消消樂遊戲",
      "developer": "Joymaster Puzzle Game Studio",
      "genre": "休闲",
      "delta": -12,
      "alert": false,
      "ai_type": "休閒益智"
    },
    {
      "rank": 47,
      "app_id": "com.fattoy.shelter",
      "app_name": "小小生存隊",
      "app_name_zh": "小小生存隊",
      "developer": "FATTOY",
      "genre": "休闲",
      "delta": -19,
      "alert": false,
      "ai_type": "模擬沙盒"
    },
    {
      "rank": 48,
      "app_id": "jp.pokemon.pokemontcgp",
      "app_name": "Pokémon TCG Pocket",
      "app_name_zh": "Pokémon TCG Pocket",
      "developer": "The Pokémon Company",
      "genre": "卡牌",
      "delta": -18,
      "alert": false,
      "ai_type": "策略對戰"
    },
    {
      "rank": 49,
      "app_id": "com.andaman.games.block.puzzle.free",
      "app_name": "Block Puzzle：Bloom Journey",
      "app_name_zh": "Block Puzzle：Bloom Journey",
      "developer": "Andaman",
      "genre": "益智",
      "delta": -7,
      "alert": false,
      "ai_type": "休閒益智"
    },
    {
      "rank": 50,
      "app_id": "com.mechanist.dream2.aos",
      "app_name": "盜夢英雄2：幻野",
      "app_name_zh": "盜夢英雄2：幻野",
      "developer": "DreamPlus Games",
      "genre": "角色扮演",
      "delta": -13,
      "alert": false,
      "ai_type": "角色扮演"
    },
    {
      "rank": 51,
      "app_id": "com.ningningstudio.kpopmagictiles",
      "app_name": "Kpop 鋼琴塊 3 - 音樂遊戲",
      "app_name_zh": "Kpop 鋼琴塊 3 - 音樂遊戲",
      "developer": "Sonata Studio: Piano Rhythm",
      "genre": "音乐",
      "delta": 12,
      "alert": false,
      "ai_type": "休閒益智"
    },
    {
      "rank": 52,
      "app_id": "com.kiloo.subwaysurf",
      "app_name": "Subway Surfers",
      "app_name_zh": "Subway Surfers",
      "developer": "SYBO Games",
      "genre": "街机",
      "delta": 116,
      "alert": false,
      "ai_type": "動作競技"
    },
    {
      "rank": 53,
      "app_id": "com.clarkstudio.screw.an.ns",
      "app_name": "Unscrew: Screw Pin Jam Puzzle",
      "app_name_zh": "Unscrew: Screw Pin Jam Puzzle",
      "developer": "CLARK STUDIO",
      "genre": "休闲",
      "delta": 60,
      "alert": false,
      "ai_type": "休閒益智"
    },
    {
      "rank": 54,
      "app_id": "com.mergegames.gossipharbor",
      "app_name": "緋聞港口：合併&故事",
      "app_name_zh": "緋聞港口：合併&故事",
      "developer": "Microfun Limited",
      "genre": "益智",
      "delta": -16,
      "alert": false,
      "ai_type": "休閒益智"
    },
    {
      "rank": 55,
      "app_id": "com.Stargazer.StellaSora",
      "app_name": "星塔旅人",
      "app_name_zh": "星塔旅人",
      "developer": "Stargazer Limited",
      "genre": "冒险",
      "delta": -34,
      "alert": false,
      "ai_type": "角色扮演"
    },
    {
      "rank": 56,
      "app_id": "com.brain.logic.joygame",
      "app_name": "Brain Puzzle 2: Logic Twist",
      "app_name_zh": "Brain Puzzle 2: Logic Twist",
      "developer": "JoyGame Studio",
      "genre": "益智",
      "delta": 24,
      "alert": false,
      "ai_type": "休閒益智"
    },
    {
      "rank": 57,
      "app_id": "com.gemnonogram.sfgame",
      "app_name": "寶石數獨：Gem Nonogram",
      "app_name_zh": "寶石數獨：Gem Nonogram",
      "developer": "SF Group",
      "genre": "文字",
      "delta": 47,
      "alert": false,
      "ai_type": "休閒益智"
    },
    {
      "rank": 58,
      "app_id": "com.eggpuzzle.platformer.run",
      "app_name": "蛋先生：解謎大師",
      "app_name_zh": "蛋先生：解謎大師",
      "developer": "Hohama Studio",
      "genre": "休闲",
      "delta": 8,
      "alert": false,
      "ai_type": "休閒益智"
    },
    {
      "rank": 59,
      "app_id": "com.linecorp.lgtoy.aos",
      "app_name": "熊大玩具",
      "app_name_zh": "熊大玩具",
      "developer": "LINE NEXT Corp.",
      "genre": "休闲",
      "delta": 60,
      "alert": false,
      "ai_type": "休閒益智"
    },
    {
      "rank": 60,
      "app_id": "com.gearpaw.defenders.td.game",
      "app_name": "齒輪獸衛隊",
      "app_name_zh": "齒輪獸衛隊",
      "developer": "Perfeggs",
      "genre": "策略",
      "delta": -14,
      "alert": false,
      "ai_type": "策略對戰"
    },
    {
      "rank": 61,
      "app_id": "com.agedstudio.word.puzzle.chengyucaicai",
      "app_name": "成語猜猜",
      "app_name_zh": "成語猜猜",
      "developer": "Aged Studio Limited",
      "genre": "文字",
      "delta": 4,
      "alert": false,
      "ai_type": "休閒益智"
    },
    {
      "rank": 62,
      "app_id": "com.wwv.global",
      "app_name": "小艦艦超勇",
      "app_name_zh": "小艦艦超勇",
      "developer": "Century Games PTE. LTD.",
      "genre": "角色扮演",
      "delta": 0,
      "alert": false,
      "ai_type": "其他"
    },
    {
      "rank": 63,
      "app_id": "com.nianticlabs.pokemongo",
      "app_name": "Pokémon GO",
      "app_name_zh": "Pokémon GO",
      "developer": "Niantic, Inc.",
      "genre": "冒险",
      "delta": -16,
      "alert": false,
      "ai_type": "角色扮演"
    },
    {
      "rank": 64,
      "app_id": "io.supercent.linkedcubic",
      "app_name": "蛇衝突 (Snake Clash)",
      "app_name_zh": "蛇衝突 (Snake Clash)",
      "developer": "Supercent, Inc.",
      "genre": "街机",
      "delta": -8,
      "alert": false,
      "ai_type": "動作競技"
    },
    {
      "rank": 65,
      "app_id": "com.king.candycrushsaga",
      "app_name": "糖果傳奇",
      "app_name_zh": "糖果傳奇",
      "developer": "King",
      "genre": "休闲",
      "delta": 40,
      "alert": false,
      "ai_type": "休閒益智"
    },
    {
      "rank": 66,
      "app_id": "com.gamovation.tileclub",
      "app_name": "Tile Club - Match Puzzle Game",
      "app_name_zh": "Tile Club - Match Puzzle Game",
      "developer": "GamoVation",
      "genre": "益智",
      "delta": -7,
      "alert": false,
      "ai_type": "休閒益智"
    },
    {
      "rank": 67,
      "app_id": "com.linecorp.LGNMSM",
      "app_name": "LINE 天外消消楽(Match Flight)",
      "app_name_zh": "LINE 天外消消楽(Match Flight)",
      "developer": "LINE (LY Corporation)",
      "genre": "益智",
      "delta": -23,
      "alert": false,
      "ai_type": "休閒益智"
    },
    {
      "rank": 68,
      "app_id": "com.choice.craft",
      "app_name": "趣穿書ChoiceCraft",
      "app_name_zh": "趣穿書ChoiceCraft",
      "developer": "SPHERE NEWRGY PTE. LTD.",
      "genre": "休闲",
      "delta": -27,
      "alert": false,
      "ai_type": "休閒益智"
    },
    {
      "rank": 69,
      "app_id": "wool.match.color.sort.jam.puzzle",
      "app_name": "毛線衝擊 - 救救小貓 顏色排序遊戲",
      "app_name_zh": "毛線衝擊 - 救救小貓 顏色排序遊戲",
      "developer": "Astrasen Play",
      "genre": "益智",
      "delta": 7,
      "alert": false,
      "ai_type": "休閒益智"
    },
    {
      "rank": 70,
      "app_id": "com.fattoy.tankpack",
      "app_name": "戰車向前冲",
      "app_name_zh": "戰車向前冲",
      "developer": "FATTOY",
      "genre": "休闲",
      "delta": 28,
      "alert": false,
      "ai_type": "休閒益智"
    },
    {
      "rank": 71,
      "app_id": "com.rekoo.pubgm",
      "app_name": "PUBG MOBILE：絕地求生M",
      "app_name_zh": "PUBG MOBILE：絕地求生M",
      "developer": "HotCool Game",
      "genre": "动作",
      "delta": 62,
      "alert": false,
      "ai_type": "動作競技"
    },
    {
      "rank": 72,
      "app_id": "com.tinymonster.android.chinesewords",
      "app_name": "漢字找茬王-糾正錯別字：詩詞成語，語文作文",
      "app_name_zh": "漢字找茬王-糾正錯別字：詩詞成語，語文作文",
      "developer": "Tiny Monster",
      "genre": "文字",
      "delta": 0,
      "alert": false,
      "ai_type": "其他"
    },
    {
      "rank": 73,
      "app_id": "io.voodoo.holeio",
      "app_name": "Hole.io",
      "app_name_zh": "Hole.io",
      "developer": "VOODOO",
      "genre": "街机",
      "delta": -5,
      "alert": false,
      "ai_type": "動作競技"
    },
    {
      "rank": 74,
      "app_id": "com.fivering.rxjh.and",
      "app_name": "熱血江湖：歸來",
      "app_name_zh": "熱血江湖：歸來",
      "developer": "5RING GAME",
      "genre": "角色扮演",
      "delta": 0,
      "alert": false,
      "ai_type": "角色扮演"
    },
    {
      "rank": 75,
      "app_id": "puzzle.merge.maid.cafe",
      "app_name": "合併女僕咖啡廳－異世界物語",
      "app_name_zh": "合併女僕咖啡廳－異世界物語",
      "developer": "HIGHSCORE GAMES",
      "genre": "益智",
      "delta": 103,
      "alert": false,
      "ai_type": "休閒益智"
    },
    {
      "rank": 76,
      "app_id": "com.funplus.ts.global",
      "app_name": "點點大作戰",
      "app_name_zh": "點點大作戰",
      "developer": "FunPlus International AG",
      "genre": "策略",
      "delta": -27,
      "alert": false,
      "ai_type": "策略對戰"
    },
    {
      "rank": 77,
      "app_id": "com.igs.TMD",
      "app_name": "滿貫大亨 - 快打旋風登場",
      "app_name_zh": "滿貫大亨 - 快打旋風登場",
      "developer": "SHIZI TECH LTD CO.",
      "genre": "赌场",
      "delta": -50,
      "alert": false,
      "ai_type": "社交賭場"
    },
    {
      "rank": 78,
      "app_id": "com.shmysusaga.gp",
      "app_name": "忍道秘傳：羈絆傳承",
      "app_name_zh": "忍道秘傳：羈絆傳承",
      "developer": "Adam Champagne",
      "genre": "动作",
      "delta": 0,
      "alert": false,
      "ai_type": "其他"
    },
    {
      "rank": 79,
      "app_id": "com.hygame.hxqq.tw.gp",
      "app_name": "華夏千秋",
      "app_name_zh": "華夏千秋",
      "developer": "HuoYuGame",
      "genre": "模拟",
      "delta": -26,
      "alert": false,
      "ai_type": "模擬沙盒"
    },
    {
      "rank": 80,
      "app_id": "io.voodoo.paper2",
      "app_name": "Paper.io 2",
      "app_name_zh": "Paper.io 2",
      "developer": "VOODOO",
      "genre": "街机",
      "delta": -23,
      "alert": false,
      "ai_type": "休閒益智"
    },
    {
      "rank": 81,
      "app_id": "com.netease.eggypartyhmt",
      "app_name": "蛋仔派對",
      "app_name_zh": "蛋仔派對",
      "developer": "EnvoyGames",
      "genre": "休闲",
      "delta": -6,
      "alert": false,
      "ai_type": "休閒益智"
    },
    {
      "rank": 82,
      "app_id": "com.global.sgdbztw",
      "app_name": "時光大爆炸",
      "app_name_zh": "時光大爆炸",
      "developer": "頑星遊戲",
      "genre": "模拟",
      "delta": 11,
      "alert": false,
      "ai_type": "模擬沙盒"
    },
    {
      "rank": 83,
      "app_id": "com.Garawell.BridgeRace",
      "app_name": "Bridge Race",
      "app_name_zh": "Bridge Race",
      "developer": "Supersonic Studios LTD",
      "genre": "休闲",
      "delta": 12,
      "alert": false,
      "ai_type": "休閒益智"
    },
    {
      "rank": 84,
      "app_id": "com.igs.starparty.aos",
      "app_name": "玩星派對",
      "app_name_zh": "玩星派對",
      "developer": "International Games System Co., Ltd.",
      "genre": "休闲",
      "delta": 7,
      "alert": false,
      "ai_type": "休閒益智"
    },
    {
      "rank": 85,
      "app_id": "io.supercent.pizzaidle",
      "app_name": "Pizza Ready",
      "app_name_zh": "Pizza Ready",
      "developer": "Supercent, Inc.",
      "genre": "模拟",
      "delta": -4,
      "alert": false,
      "ai_type": "模擬沙盒"
    },
    {
      "rank": 86,
      "app_id": "com.igg.android.doomsdaylastsurvivors",
      "app_name": "黎明再現(Doomsday: Last Survivors)",
      "app_name_zh": "黎明再現(Doomsday: Last Survivors)",
      "developer": "IGG.COM",
      "genre": "策略",
      "delta": -13,
      "alert": false,
      "ai_type": "策略對戰"
    },
    {
      "rank": 87,
      "app_id": "com.nebula.mahjongtile",
      "app_name": "Mahjong Wonders™",
      "app_name_zh": "Mahjong Wonders™",
      "developer": "Nebula  Studio",
      "genre": "桌面和棋类",
      "delta": -35,
      "alert": false,
      "ai_type": "休閒益智"
    },
    {
      "rank": 88,
      "app_id": "com.linecorp.LGSNPTW",
      "app_name": "LINE 數獨達人",
      "app_name_zh": "LINE 數獨達人",
      "developer": "LINE (LY Corporation)",
      "genre": "街机",
      "delta": 53,
      "alert": false,
      "ai_type": "休閒益智"
    },
    {
      "rank": 89,
      "app_id": "com.color.pixel.shooter",
      "app_name": "Color Pixel Shooter",
      "app_name_zh": "Color Pixel Shooter",
      "developer": "FUNFINITY HK",
      "genre": "益智",
      "delta": 0,
      "alert": false,
      "ai_type": "其他"
    },
    {
      "rank": 90,
      "app_id": "com.linecorp.LGATF",
      "app_name": "LINE Rangers 放置戰爭",
      "app_name_zh": "LINE Rangers 放置戰爭",
      "developer": "LINE (LY Corporation)",
      "genre": "角色扮演",
      "delta": 0,
      "alert": false,
      "ai_type": "角色扮演"
    },
    {
      "rank": 91,
      "app_id": "com.godplace.twgp",
      "app_name": "第七天災",
      "app_name_zh": "第七天災",
      "developer": "SPGFun",
      "genre": "角色扮演",
      "delta": 54,
      "alert": false,
      "ai_type": "角色扮演"
    },
    {
      "rank": 92,
      "app_id": "com.youmusic.magictiles",
      "app_name": "Magic Tiles 3™ - 鋼琴遊戲",
      "app_name_zh": "Magic Tiles 3™ - 鋼琴遊戲",
      "developer": "AMANOTES PTE. LTD.",
      "genre": "音乐",
      "delta": -22,
      "alert": false,
      "ai_type": "休閒益智"
    },
    {
      "rank": 93,
      "app_id": "com.igs.mjstar31",
      "app_name": "麻將 明星3缺1麻將",
      "app_name_zh": "麻將 明星3缺1麻將",
      "developer": "International Games System Co., Ltd.",
      "genre": "赌场",
      "delta": -6,
      "alert": false,
      "ai_type": "社交賭場"
    },
    {
      "rank": 94,
      "app_id": "com.mathbrain.sudoku",
      "app_name": "數獨大師 - Sudoku Master!",
      "app_name_zh": "數獨大師 - Sudoku Master!",
      "developer": "HungryStudio",
      "genre": "益智",
      "delta": -12,
      "alert": false,
      "ai_type": "休閒益智"
    },
    {
      "rank": 95,
      "app_id": "com.playrix.township",
      "app_name": "夢想小鎮",
      "app_name_zh": "夢想小鎮",
      "developer": "Playrix",
      "genre": "休闲",
      "delta": -24,
      "alert": false,
      "ai_type": "模擬沙盒"
    },
    {
      "rank": 96,
      "app_id": "com.NewFolderGames.IAmMonkey",
      "app_name": "I Am Monkey",
      "app_name_zh": "I Am Monkey",
      "developer": "Estoty",
      "genre": "模拟",
      "delta": 0,
      "alert": false,
      "ai_type": "其他"
    },
    {
      "rank": 97,
      "app_id": "com.godgame.mj.android",
      "app_name": "麻將 神來也麻將－台灣16張、麻雀",
      "app_name_zh": "麻將 神來也麻將－台灣16張、麻雀",
      "developer": "Gamesofa Inc.",
      "genre": "赌场",
      "delta": 51,
      "alert": false,
      "ai_type": "社交賭場"
    },
    {
      "rank": 98,
      "app_id": "com.Nekootan.kfkjos.google",
      "app_name": "OverField",
      "app_name_zh": "OverField",
      "developer": "INUTAN Limited",
      "genre": "角色扮演",
      "delta": 0,
      "alert": false,
      "ai_type": "其他"
    },
    {
      "rank": 99,
      "app_id": "com.m88.idleXX",
      "app_name": "杖劍傳說：坎斯汀之約",
      "app_name_zh": "杖劍傳說：坎斯汀之約",
      "developer": "LTGAMES GLOBAL",
      "genre": "角色扮演",
      "delta": -13,
      "alert": false,
      "ai_type": "角色扮演"
    },
    {
      "rank": 100,
      "app_id": "jp.co.ponos.battlecatstw",
      "app_name": "貓咪大戰爭",
      "app_name_zh": "貓咪大戰爭",
      "developer": "PONOS Corporation",
      "genre": "休闲",
      "delta": 0,
      "alert": false,
      "ai_type": "休閒益智"
    },
    {
      "rank": 101,
      "app_id": "com.mover.twzqzs",
      "app_name": "最強宗師",
      "app_name_zh": "最強宗師",
      "developer": "Mover Games Limited",
      "genre": "卡牌",
      "delta": -27,
      "alert": false,
      "ai_type": "策略對戰"
    },
    {
      "rank": 102,
      "app_id": "com.zm.blockaway",
      "app_name": "Block Away - Tap Out Puzzle",
      "app_name_zh": "Block Away - Tap Out Puzzle",
      "developer": "Tripledot Studios Limited",
      "genre": "益智",
      "delta": 0,
      "alert": false,
      "ai_type": "休閒益智"
    },
    {
      "rank": 103,
      "app_id": "com.kiwigames.happycitizen.gp",
      "app_name": "幸福都市 - 市長模擬器",
      "app_name_zh": "幸福都市 - 市長模擬器",
      "developer": "LifeSim",
      "genre": "模拟",
      "delta": -48,
      "alert": false,
      "ai_type": "模擬沙盒"
    },
    {
      "rank": 104,
      "app_id": "com.rsgjmnq.sfchuanglian",
      "app_name": "人生軌跡模擬器",
      "app_name_zh": "人生軌跡模擬器",
      "developer": "SF Group",
      "genre": "模拟",
      "delta": -46,
      "alert": false,
      "ai_type": "模擬沙盒"
    },
    {
      "rank": 105,
      "app_id": "com.goodluck777.panther",
      "app_name": "金好運－戰神賽特、吉宗、南國育、黃門喝、捕魚、老虎機、麻將",
      "app_name_zh": "金好運－戰神賽特、吉宗、南國育、黃門喝、捕魚、老虎機、麻將",
      "developer": "ARC PLAY LTD CO.",
      "genre": "赌场",
      "delta": 51,
      "alert": false,
      "ai_type": "社交賭場"
    },
    {
      "rank": 106,
      "app_id": "com.i89trillion.strategy.rising",
      "app_name": "War Inc: Rising",
      "app_name_zh": "War Inc: Rising",
      "developer": "Fastone Games",
      "genre": "策略",
      "delta": -7,
      "alert": false,
      "ai_type": "策略對戰"
    },
    {
      "rank": 107,
      "app_id": "com.tfv.block.line.fill.puzzle",
      "app_name": "Single Line Block Fill Puzzle",
      "app_name_zh": "Single Line Block Fill Puzzle",
      "developer": "The Fashion Valley",
      "genre": "益智",
      "delta": -1,
      "alert": false,
      "ai_type": "休閒益智"
    },
    {
      "rank": 108,
      "app_id": "com.jumbo.yirufa",
      "app_name": "包你發-王識賢、安心亞推薦娛樂城-賽特1000上線千倍紅球雨",
      "app_name_zh": "包你發-王識賢、安心亞推薦娛樂城-賽特1000上線千倍紅球雨",
      "developer": "YILE TECHNOLOGY CO., LTD.",
      "genre": "赌场",
      "delta": 19,
      "alert": false,
      "ai_type": "社交賭場"
    },
    {
      "rank": 109,
      "app_id": "com.linecorp.LGFARM",
      "app_name": "LINE 熊大農場",
      "app_name_zh": "LINE 熊大農場",
      "developer": "LINE (LY Corporation)",
      "genre": "模拟",
      "delta": 19,
      "alert": false,
      "ai_type": "模擬沙盒"
    },
    {
      "rank": 110,
      "app_id": "com.gtsy.annoying.punch.game",
      "app_name": "Annoying Uncle - 拳擊遊戲",
      "app_name_zh": "Annoying Uncle - 拳擊遊戲",
      "developer": "GOOD TO SEE YOU",
      "genre": "模拟",
      "delta": 21,
      "alert": false,
      "ai_type": "模擬沙盒"
    },
    {
      "rank": 111,
      "app_id": "onetap.game.fruit.fall",
      "app_name": "Fruit Hole - Juicy Jam",
      "app_name_zh": "Fruit Hole - Juicy Jam",
      "developer": "Onetap Global",
      "genre": "益智",
      "delta": 0,
      "alert": false,
      "ai_type": "休閒益智"
    },
    {
      "rank": 112,
      "app_id": "com.higame.par.idol.prank.video.call.chat.phone.fun",
      "app_name": "Idol Prank Video Call & Chat",
      "app_name_zh": "Idol Prank Video Call & Chat",
      "developer": "HIGAME GLOBAL",
      "genre": "休闲",
      "delta": 31,
      "alert": false,
      "ai_type": "休閒益智"
    },
    {
      "rank": 113,
      "app_id": "com.panstudio.gplay.duetnightabyss.arpg.global",
      "app_name": "二重螺旋",
      "app_name_zh": "二重螺旋",
      "developer": "Hong Kong Spiral Rising Technology Co., Limited",
      "genre": "角色扮演",
      "delta": 0,
      "alert": false,
      "ai_type": "角色扮演"
    },
    {
      "rank": 114,
      "app_id": "com.dts.freefireth",
      "app_name": "Free Fire",
      "app_name_zh": "Free Fire",
      "developer": "GARENA INTERNATIONAL I",
      "genre": "动作",
      "delta": 46,
      "alert": false,
      "ai_type": "動作競技"
    },
    {
      "rank": 115,
      "app_id": "com.ncsoft.lineagew",
      "app_name": "天堂W",
      "app_name_zh": "天堂W",
      "developer": "NCSOFT",
      "genre": "角色扮演",
      "delta": 14,
      "alert": false,
      "ai_type": "角色扮演"
    },
    {
      "rank": 116,
      "app_id": "com.tappy.minigames.challenge",
      "app_name": "Tappy Minigames Challenge",
      "app_name_zh": "Tappy Minigames Challenge",
      "developer": "ThunderstormStudio",
      "genre": "休闲",
      "delta": 20,
      "alert": false,
      "ai_type": "休閒益智"
    },
    {
      "rank": 117,
      "app_id": "com.dimsumshop.sort.com",
      "app_name": "我的點心鋪",
      "app_name_zh": "我的點心鋪",
      "developer": "Ehsan Khaled",
      "genre": "益智",
      "delta": -53,
      "alert": false,
      "ai_type": "休閒益智"
    },
    {
      "rank": 118,
      "app_id": "com.abi.busjam.sortpuzzle",
      "app_name": "巴士逃生 - 交通堵塞",
      "app_name_zh": "巴士逃生 - 交通堵塞",
      "developer": "ABI GAME",
      "genre": "益智",
      "delta": 67,
      "alert": false,
      "ai_type": "休閒益智"
    },
    {
      "rank": 119,
      "app_id": "com.HoYoverse.hkrpgoversea",
      "app_name": "崩壞：星穹鐵道",
      "app_name_zh": "崩壞：星穹鐵道",
      "developer": "COGNOSPHERE PTE. LTD.",
      "genre": "冒险",
      "delta": 0,
      "alert": false,
      "ai_type": "角色扮演"
    },
    {
      "rank": 120,
      "app_id": "com.topwar.gp",
      "app_name": "口袋奇兵（Top War）-超休閒的策略遊戲",
      "app_name_zh": "口袋奇兵（Top War）-超休閒的策略遊戲",
      "developer": "RiverGame",
      "genre": "策略",
      "delta": 0,
      "alert": false,
      "ai_type": "策略對戰"
    },
    {
      "rank": 121,
      "app_id": "com.puzzle.impact.hero",
      "app_name": "暗影英雄：突襲",
      "app_name_zh": "暗影英雄：突襲",
      "developer": "Glacier entertainment",
      "genre": "卡牌",
      "delta": -70,
      "alert": false,
      "ai_type": "策略對戰"
    },
    {
      "rank": 122,
      "app_id": "com.hermes.mk.asia",
      "app_name": "世界計畫 繽紛舞台！feat. 初音未來",
      "app_name_zh": "世界計畫 繽紛舞台！feat. 初音未來",
      "developer": "Nuverse",
      "genre": "音乐",
      "delta": -11,
      "alert": false,
      "ai_type": "其他"
    },
    {
      "rank": 123,
      "app_id": "screw.puzzle.match3.brain.puzz",
      "app_name": "擰螺絲消除專家 - 擰開螺絲和螺帽的解謎遊戲，好玩的螺栓遊戲",
      "app_name_zh": "擰螺絲消除專家 - 擰開螺絲和螺帽的解謎遊戲，好玩的螺栓遊戲",
      "developer": "Astrasen Play",
      "genre": "益智",
      "delta": 48,
      "alert": false,
      "ai_type": "休閒益智"
    },
    {
      "rank": 124,
      "app_id": "word.games.puzzle.offline.games",
      "app_name": "成語填填看 - 單字測驗、單字和文字遊戲、大腦訓練和現實遊戲",
      "app_name_zh": "成語填填看 - 單字測驗、單字和文字遊戲、大腦訓練和現實遊戲",
      "developer": "Astrasen Play",
      "genre": "文字",
      "delta": 22,
      "alert": false,
      "ai_type": "休閒益智"
    },
    {
      "rank": 125,
      "app_id": "com.goplaytoday.sniper3d",
      "app_name": "Sniper Area: Sniper shooter",
      "app_name_zh": "Sniper Area: Sniper shooter",
      "developer": "Studio WW Games",
      "genre": "动作",
      "delta": -15,
      "alert": false,
      "ai_type": "動作競技"
    },
    {
      "rank": 126,
      "app_id": "com.bigcake.android.mahjongmatch",
      "app_name": "每日麻將配對",
      "app_name_zh": "每日麻將配對",
      "developer": "Big Cake",
      "genre": "桌面和棋类",
      "delta": 12,
      "alert": false,
      "ai_type": "休閒益智"
    },
    {
      "rank": 127,
      "app_id": "com.yolo.hiddenobjects",
      "app_name": "Find Hidden Objects - Spot It!",
      "app_name_zh": "Find Hidden Objects - Spot It!",
      "developer": "Yolo Game Studios",
      "genre": "益智",
      "delta": -5,
      "alert": false,
      "ai_type": "休閒益智"
    },
    {
      "rank": 128,
      "app_id": "game.xin.hd.g",
      "app_name": "星城Online-普發一萬現領現玩",
      "app_name_zh": "星城Online-普發一萬現領現玩",
      "developer": "網銀國際 股份有限 公司",
      "genre": "赌场",
      "delta": 53,
      "alert": false,
      "ai_type": "社交賭場"
    },
    {
      "rank": 129,
      "app_id": "com.actgames.HelloKittyMDS",
      "app_name": "Hello Kitty My Dream Store",
      "app_name_zh": "Hello Kitty My Dream Store",
      "developer": "ACTGames Co., Ltd.",
      "genre": "益智",
      "delta": 68,
      "alert": false,
      "ai_type": "休閒益智"
    },
    {
      "rank": 130,
      "app_id": "com.hg.dungeonofexile.gl",
      "app_name": "DoE：流亡地牢—Mini Diablo三分鐘暗黑解壓",
      "app_name_zh": "DoE：流亡地牢—Mini Diablo三分鐘暗黑解壓",
      "developer": "HUNT Games Company Limited",
      "genre": "动作",
      "delta": -34,
      "alert": false,
      "ai_type": "角色扮演"
    },
    {
      "rank": 131,
      "app_id": "com.readygo.dark.gp",
      "app_name": "Dark War Survival",
      "app_name_zh": "Dark War Survival",
      "developer": "Florere Game",
      "genre": "策略",
      "delta": -43,
      "alert": false,
      "ai_type": "策略對戰"
    },
    {
      "rank": 132,
      "app_id": "com.AlexHK.BitCoiner",
      "app_name": "BitCoiner",
      "app_name_zh": "BitCoiner",
      "developer": "Yso Corp",
      "genre": "模拟",
      "delta": -48,
      "alert": false,
      "ai_type": "模擬沙盒"
    },
    {
      "rank": 133,
      "app_id": "easy.sudoku.puzzle.solver.free",
      "app_name": "數獨 - 經典數獨謎題",
      "app_name_zh": "數獨 - 經典數獨謎題",
      "developer": "Oakever Games",
      "genre": "益智",
      "delta": 25,
      "alert": false,
      "ai_type": "休閒益智"
    },
    {
      "rank": 134,
      "app_id": "com.cyberjoy.galaxydefense",
      "app_name": "太空防禦(Galaxy Defense)",
      "app_name_zh": "太空防禦(Galaxy Defense)",
      "developer": "CyberJoy Games",
      "genre": "策略",
      "delta": -31,
      "alert": false,
      "ai_type": "策略對戰"
    },
    {
      "rank": 135,
      "app_id": "com.vincentb.MobControl",
      "app_name": "Mob Control",
      "app_name_zh": "Mob Control",
      "developer": "VOODOO",
      "genre": "街机",
      "delta": 0,
      "alert": false,
      "ai_type": "動作競技"
    },
    {
      "rank": 136,
      "app_id": "com.paurau.MakeHer",
      "app_name": "Move People",
      "app_name_zh": "Move People",
      "developer": "Supersonic Studios LTD",
      "genre": "模拟",
      "delta": 0,
      "alert": false,
      "ai_type": "模擬沙盒"
    },
    {
      "rank": 137,
      "app_id": "com.boge.lgmahjong",
      "app_name": "嚦咕麻將-戰神賽特2首發登場",
      "app_name_zh": "嚦咕麻將-戰神賽特2首發登場",
      "developer": "BOGE NETWORK TECHNOLOGY LIMITED",
      "genre": "赌场",
      "delta": 0,
      "alert": false,
      "ai_type": "社交賭場"
    },
    {
      "rank": 138,
      "app_id": "com.playstrom.hero.tower",
      "app_name": "TDS - Tower Destiny Survive",
      "app_name_zh": "TDS - Tower Destiny Survive",
      "developer": "SayGames Ltd",
      "genre": "动作",
      "delta": -14,
      "alert": false,
      "ai_type": "策略對戰"
    },
    {
      "rank": 139,
      "app_id": "com.garena.game.codm",
      "app_name": "決勝時刻®: Mobile - Garena",
      "app_name_zh": "決勝時刻®: Mobile - Garena",
      "developer": "Garena Mobile Private",
      "genre": "动作",
      "delta": 16,
      "alert": false,
      "ai_type": "動作競技"
    },
    {
      "rank": 140,
      "app_id": "com.abi.cook.chill",
      "app_name": "Cookingdom - 烹飪之地",
      "app_name_zh": "Cookingdom - 烹飪之地",
      "developer": "ABI Games Studio",
      "genre": "模拟",
      "delta": -39,
      "alert": false,
      "ai_type": "模擬沙盒"
    },
    {
      "rank": 141,
      "app_id": "com.fatmerge.global",
      "app_name": "食光旅行",
      "app_name_zh": "食光旅行",
      "developer": "Century Games PTE. LTD.",
      "genre": "休闲",
      "delta": -4,
      "alert": false,
      "ai_type": "休閒益智"
    },
    {
      "rank": 142,
      "app_id": "com.miracle.savethedoge.an",
      "app_name": "Save the Doge",
      "app_name_zh": "Save the Doge",
      "developer": "WONDER GROUP",
      "genre": "益智",
      "delta": -82,
      "alert": false,
      "ai_type": "休閒益智"
    },
    {
      "rank": 143,
      "app_id": "solitaire.word.association.connections.puzzle",
      "app_name": "字詞接龍",
      "app_name_zh": "字詞接龍",
      "developer": "BitEpoch",
      "genre": "文字",
      "delta": 0,
      "alert": false,
      "ai_type": "其他"
    },
    {
      "rank": 144,
      "app_id": "com.htt.alpha.shooter.fps",
      "app_name": "Monster Shooter: Survival FPS",
      "app_name_zh": "Monster Shooter: Survival FPS",
      "developer": "Unicorn Studio Official",
      "genre": "动作",
      "delta": 19,
      "alert": false,
      "ai_type": "動作競技"
    },
    {
      "rank": 145,
      "app_id": "com.media720.games2020",
      "app_name": "離線遊戲: 無網單機好玩的桌遊 - Offline 100+",
      "app_name_zh": "離線遊戲: 無網單機好玩的桌遊 - Offline 100+",
      "developer": "Fun Offline Games",
      "genre": "休闲",
      "delta": 14,
      "alert": false,
      "ai_type": "休閒益智"
    },
    {
      "rank": 146,
      "app_id": "com.ys.gg.xbdzz",
      "app_name": "小兵來支援！",
      "app_name_zh": "小兵來支援！",
      "developer": "HAPPY TIME GAMES",
      "genre": "卡牌",
      "delta": 0,
      "alert": false,
      "ai_type": "策略對戰"
    },
    {
      "rank": 147,
      "app_id": "com.idle.drift",
      "app_name": "Idle Drift:JDM Race",
      "app_name_zh": "Idle Drift:JDM Race",
      "developer": "Solid Games",
      "genre": "休闲",
      "delta": 0,
      "alert": false,
      "ai_type": "其他"
    },
    {
      "rank": 148,
      "app_id": "puzzle.snakes.puzzle.slithereat.gaming",
      "app_name": "Snake Puzzle: Slither to Eat",
      "app_name_zh": "Snake Puzzle: Slither to Eat",
      "developer": "UniPuzz Games",
      "genre": "益智",
      "delta": -54,
      "alert": false,
      "ai_type": "休閒益智"
    },
    {
      "rank": 149,
      "app_id": "com.cliffs.pro.cell.building.crazy.clever.craft",
      "app_name": "Block Crazy Robo World Craft",
      "app_name_zh": "Block Crazy Robo World Craft",
      "developer": "Prokids Studio",
      "genre": "模拟",
      "delta": -60,
      "alert": false,
      "ai_type": "模擬沙盒"
    },
    {
      "rank": 150,
      "app_id": "music.brainrot.relax.magic.beat.piano",
      "app_name": "鋼琴模因：節拍音樂遊戲秀",
      "app_name_zh": "鋼琴模因：節拍音樂遊戲秀",
      "developer": "PulseBeat Studios",
      "genre": "音乐",
      "delta": 0,
      "alert": false,
      "ai_type": "其他"
    },
    {
      "rank": 151,
      "app_id": "com.sand.color.painting.sort.puzzle",
      "app_name": "Sand Frenzy",
      "app_name_zh": "Sand Frenzy",
      "developer": "Wing Soft",
      "genre": "益智",
      "delta": 0,
      "alert": false,
      "ai_type": "其他"
    },
    {
      "rank": 152,
      "app_id": "magic.hop.beat.tile.music",
      "app_name": "音樂節奏遊戲：球球遊戲 & 鋼琴遊戲",
      "app_name_zh": "音樂節奏遊戲：球球遊戲 & 鋼琴遊戲",
      "developer": "Beatwave Studio",
      "genre": "音乐",
      "delta": -44,
      "alert": false,
      "ai_type": "休閒益智"
    },
    {
      "rank": 153,
      "app_id": "com.bunbunstudio.magicblocktiles",
      "app_name": "音乐钢琴 7: 极速歌曲游戏",
      "app_name_zh": "音乐钢琴 7: 极速歌曲游戏",
      "developer": "Melodya Muses",
      "genre": "音乐",
      "delta": -92,
      "alert": false,
      "ai_type": "休閒益智"
    },
    {
      "rank": 154,
      "app_id": "com.DigiJello.EidolonsCross",
      "app_name": "幻牌交鋒",
      "app_name_zh": "幻牌交鋒",
      "developer": "DIGI JELLO LTD.",
      "genre": "策略",
      "delta": 0,
      "alert": false,
      "ai_type": "策略對戰"
    },
    {
      "rank": 155,
      "app_id": "com.Earthkwak.Platformer",
      "app_name": "Super Bear Adventure",
      "app_name_zh": "Super Bear Adventure",
      "developer": "Earthkwak Games",
      "genre": "冒险",
      "delta": 34,
      "alert": false,
      "ai_type": "角色扮演"
    },
    {
      "rank": 156,
      "app_id": "com.msyeti.gyem",
      "app_name": "秘境道館試煉",
      "app_name_zh": "秘境道館試煉",
      "developer": "SIRIUS GAMES",
      "genre": "角色扮演",
      "delta": 0,
      "alert": false,
      "ai_type": "其他"
    },
    {
      "rank": 157,
      "app_id": "gg.sunday.dog.escape.puzzle",
      "app_name": "Dog Escape",
      "app_name_zh": "Dog Escape",
      "developer": "Sunday.gg",
      "genre": "休闲",
      "delta": 0,
      "alert": false,
      "ai_type": "休閒益智"
    },
    {
      "rank": 158,
      "app_id": "com.cryptoapps.craftarena",
      "app_name": "Craftarena",
      "app_name_zh": "Craftarena",
      "developer": "CRYPTO FINANCIAL SOLUTION SOFTWARE COMPANY LIMITED",
      "genre": "模拟",
      "delta": 0,
      "alert": false,
      "ai_type": "其他"
    },
    {
      "rank": 159,
      "app_id": "com.greenmushroom.boomblitz.gp",
      "app_name": "王國之歌（Top Heroes）",
      "app_name_zh": "王國之歌（Top Heroes）",
      "developer": "RiverGame",
      "genre": "策略",
      "delta": -47,
      "alert": false,
      "ai_type": "策略對戰"
    },
    {
      "rank": 160,
      "app_id": "com.zzdmx.sfgame",
      "app_name": "轉轉大冒險",
      "app_name_zh": "轉轉大冒險",
      "developer": "SF Group",
      "genre": "休闲",
      "delta": 0,
      "alert": false,
      "ai_type": "其他"
    },
    {
      "rank": 161,
      "app_id": "com.linecorp.LGSTTTW",
      "app_name": "LINE 秘寶挖挖哇",
      "app_name_zh": "LINE 秘寶挖挖哇",
      "developer": "LINE (LY Corporation)",
      "genre": "益智",
      "delta": -94,
      "alert": false,
      "ai_type": "休閒益智"
    },
    {
      "rank": 162,
      "app_id": "com.backfirst.sfgame",
      "app_name": "末世之旅-逆襲求生",
      "app_name_zh": "末世之旅-逆襲求生",
      "developer": "SF Group",
      "genre": "模拟",
      "delta": 0,
      "alert": false,
      "ai_type": "其他"
    },
    {
      "rank": 163,
      "app_id": "math.puzzle.games.crossmath.number.puzzles.free",
      "app_name": "數學益智遊戲 - Crossmath",
      "app_name_zh": "數學益智遊戲 - Crossmath",
      "developer": "Guru Puzzle Game",
      "genre": "益智",
      "delta": 1,
      "alert": false,
      "ai_type": "休閒益智"
    },
    {
      "rank": 164,
      "app_id": "game.lantern.ckxx",
      "app_name": "卡包修仙",
      "app_name_zh": "卡包修仙",
      "developer": "lantern",
      "genre": "模拟",
      "delta": -116,
      "alert": false,
      "ai_type": "模擬沙盒"
    },
    {
      "rank": 165,
      "app_id": "com.sh.fidget.toys.mini.relaxing.antistress.games",
      "app_name": "迷你放鬆遊戲 - pop it",
      "app_name_zh": "迷你放鬆遊戲 - pop it",
      "developer": "stick hunter",
      "genre": "休闲",
      "delta": -68,
      "alert": false,
      "ai_type": "休閒益智"
    },
    {
      "rank": 166,
      "app_id": "com.dlw.gat.google",
      "app_name": "戰靈異聞社-神話鍾馗搶先玩",
      "app_name_zh": "戰靈異聞社-神話鍾馗搶先玩",
      "developer": "XStargames",
      "genre": "角色扮演",
      "delta": 4,
      "alert": false,
      "ai_type": "角色扮演"
    },
    {
      "rank": 167,
      "app_id": "com.fc.sdk.block.escape",
      "app_name": "Block Escape",
      "app_name_zh": "Block Escape",
      "developer": "Think Different FC.",
      "genre": "益智",
      "delta": 0,
      "alert": false,
      "ai_type": "其他"
    },
    {
      "rank": 168,
      "app_id": "com.JindoBlu.OfflineGames",
      "app_name": "Offline Games - No Wifi Games",
      "app_name_zh": "Offline Games - No Wifi Games",
      "developer": "JindoBlu",
      "genre": "休闲",
      "delta": 0,
      "alert": false,
      "ai_type": "休閒益智"
    },
    {
      "rank": 169,
      "app_id": "com.minipact.eartharcade",
      "app_name": "地球娛樂室 M: Torong Wanted",
      "app_name_zh": "地球娛樂室 M: Torong Wanted",
      "developer": "Minipact Games",
      "genre": "休闲",
      "delta": -107,
      "alert": false,
      "ai_type": "休閒益智"
    },
    {
      "rank": 170,
      "app_id": "com.v20.gptw",
      "app_name": "邪門鬼道",
      "app_name_zh": "邪門鬼道",
      "developer": "SPGFun",
      "genre": "角色扮演",
      "delta": 12,
      "alert": false,
      "ai_type": "角色扮演"
    },
    {
      "rank": 171,
      "app_id": "com.tripledot.blockbash",
      "app_name": "Woodoku Blast",
      "app_name_zh": "Woodoku Blast",
      "developer": "Tripledot Studios Limited",
      "genre": "益智",
      "delta": 0,
      "alert": false,
      "ai_type": "休閒益智"
    },
    {
      "rank": 172,
      "app_id": "io.randomco.travel",
      "app_name": "Travel Town - Merge Adventure",
      "app_name_zh": "Travel Town - Merge Adventure",
      "developer": "Magmatic Games LTD",
      "genre": "益智",
      "delta": -33,
      "alert": false,
      "ai_type": "休閒益智"
    },
    {
      "rank": 173,
      "app_id": "com.miniclip.eightballpool",
      "app_name": "8 Ball Pool",
      "app_name_zh": "8 Ball Pool",
      "developer": "Miniclip.com",
      "genre": "体育",
      "delta": 0,
      "alert": false,
      "ai_type": "動作競技"
    },
    {
      "rank": 174,
      "app_id": "com.byaliens.bidwars4",
      "app_name": "Bid Wars: Auction Master 3D",
      "app_name_zh": "Bid Wars: Auction Master 3D",
      "developer": "By Aliens L.L.C-F.Z",
      "genre": "模拟",
      "delta": -164,
      "alert": false,
      "ai_type": "模擬沙盒"
    },
    {
      "rank": 175,
      "app_id": "com.pd.vehiclemasters",
      "app_name": "Vehicle Masters",
      "app_name_zh": "Vehicle Masters",
      "developer": "SayGames Ltd",
      "genre": "模拟",
      "delta": -55,
      "alert": false,
      "ai_type": "模擬沙盒"
    },
    {
      "rank": 176,
      "app_id": "com.higame.annoying.tricky.story.puzzle.game",
      "app_name": "Tricky Prank: Annoying Quest",
      "app_name_zh": "Tricky Prank: Annoying Quest",
      "developer": "HIGAME Studio",
      "genre": "益智",
      "delta": 0,
      "alert": false,
      "ai_type": "休閒益智"
    },
    {
      "rank": 177,
      "app_id": "com.hp.prison.runner3d.obby.parkour",
      "app_name": "Prison Blox: Obby 3D Parkour",
      "app_name_zh": "Prison Blox: Obby 3D Parkour",
      "developer": "HIGAME LTD.",
      "genre": "休闲",
      "delta": 0,
      "alert": false,
      "ai_type": "其他"
    },
    {
      "rank": 178,
      "app_id": "com.oceantun.basirss",
      "app_name": "Ocean Club-Fish Fight",
      "app_name_zh": "Ocean Club-Fish Fight",
      "developer": "GreenTTeaGame",
      "genre": "休闲",
      "delta": 0,
      "alert": false,
      "ai_type": "其他"
    },
    {
      "rank": 179,
      "app_id": "com.Polystation.BuildABabe",
      "app_name": "Build A Queen",
      "app_name_zh": "Build A Queen",
      "developer": "Supersonic Studios LTD",
      "genre": "休闲",
      "delta": 20,
      "alert": false,
      "ai_type": "休閒益智"
    },
    {
      "rank": 180,
      "app_id": "com.funfinity.knitzy.thread",
      "app_name": "Color Knitzy",
      "app_name_zh": "Color Knitzy",
      "developer": "FUNFINITY HK",
      "genre": "益智",
      "delta": -26,
      "alert": false,
      "ai_type": "休閒益智"
    },
    {
      "rank": 181,
      "app_id": "com.grandgames.magicsort",
      "app_name": "Magic Sort!",
      "app_name_zh": "Magic Sort!",
      "developer": "Grand Games A.Ş.",
      "genre": "益智",
      "delta": -72,
      "alert": false,
      "ai_type": "休閒益智"
    },
    {
      "rank": 182,
      "app_id": "com.haegin.playtogether",
      "app_name": "天天玩樂園：我的農場",
      "app_name_zh": "天天玩樂園：我的農場",
      "developer": "HAEGIN Co., Ltd.",
      "genre": "休闲",
      "delta": 0,
      "alert": false,
      "ai_type": "模擬沙盒"
    },
    {
      "rank": 183,
      "app_id": "com.igg.android.lordsmobile",
      "app_name": "王國紀元 (Lords Mobile)：全面戰爭",
      "app_name_zh": "王國紀元 (Lords Mobile)：全面戰爭",
      "developer": "IGG.COM",
      "genre": "策略",
      "delta": -41,
      "alert": false,
      "ai_type": "策略對戰"
    },
    {
      "rank": 184,
      "app_id": "com.whoyaho.tanghulu",
      "app_name": "糖葫蘆達人－便利店、學校午餐、聖代咖啡館吃播ASMR",
      "app_name_zh": "糖葫蘆達人－便利店、學校午餐、聖代咖啡館吃播ASMR",
      "developer": "Whoyaho Corp.",
      "genre": "模拟",
      "delta": -32,
      "alert": false,
      "ai_type": "模擬沙盒"
    },
    {
      "rank": 185,
      "app_id": "com.crazy.bricks.android",
      "app_name": "Crazy Bricks Destroyer",
      "app_name_zh": "Crazy Bricks Destroyer",
      "developer": "LeisureLab Studios",
      "genre": "休闲",
      "delta": -45,
      "alert": false,
      "ai_type": "休閒益智"
    },
    {
      "rank": 186,
      "app_id": "com.dcjnmed.jifqq",
      "app_name": "Screw Guru",
      "app_name_zh": "Screw Guru",
      "developer": "Supersonic Studios LTD",
      "genre": "休闲",
      "delta": 0,
      "alert": false,
      "ai_type": "其他"
    },
    {
      "rank": 187,
      "app_id": "com.uc.minigame.relax",
      "app_name": "Mini Games: Brainrot Challenge",
      "app_name_zh": "Mini Games: Brainrot Challenge",
      "developer": "Unicorn Studio Official",
      "genre": "休闲",
      "delta": -18,
      "alert": false,
      "ai_type": "休閒益智"
    },
    {
      "rank": 188,
      "app_id": "com.futureplay.mergematch",
      "app_name": "Merge Gardens",
      "app_name_zh": "Merge Gardens",
      "developer": "Futureplay",
      "genre": "益智",
      "delta": -176,
      "alert": false,
      "ai_type": "休閒益智"
    },
    {
      "rank": 189,
      "app_id": "com.haunteddorm.mihuan",
      "app_name": "Haunted Dorm - 猛鬼宿舍",
      "app_name_zh": "Haunted Dorm - 猛鬼宿舍",
      "developer": "Mihuan Limited",
      "genre": "策略",
      "delta": -17,
      "alert": false,
      "ai_type": "策略對戰"
    },
    {
      "rank": 190,
      "app_id": "pics.karaage.yokaibi",
      "app_name": "妖怪美少女 二選一",
      "app_name_zh": "妖怪美少女 二選一",
      "developer": "KARAAGE GAMES LLC.",
      "genre": "休闲",
      "delta": -83,
      "alert": false,
      "ai_type": "休閒益智"
    },
    {
      "rank": 191,
      "app_id": "com.mxdzz.tw.and",
      "app_name": "菇勇者傳說-全新射擊玩法",
      "app_name_zh": "菇勇者傳說-全新射擊玩法",
      "developer": "Joy Nice Games",
      "genre": "角色扮演",
      "delta": 0,
      "alert": false,
      "ai_type": "角色扮演"
    },
    {
      "rank": 192,
      "app_id": "com.tgc.sky.android",
      "app_name": "Sky光·遇",
      "app_name_zh": "Sky光·遇",
      "developer": "thatgamecompany inc",
      "genre": "角色扮演",
      "delta": -58,
      "alert": false,
      "ai_type": "角色扮演"
    },
    {
      "rank": 193,
      "app_id": "com.gdbw.auel",
      "app_name": "神龍戰士",
      "app_name_zh": "神龍戰士",
      "developer": "LEAF NOVEL",
      "genre": "角色扮演",
      "delta": -40,
      "alert": false,
      "ai_type": "角色扮演"
    },
    {
      "rank": 194,
      "app_id": "air.tw.com.bonuswinner.bwmj16tw",
      "app_name": "麻將 宅神爺麻將-全新豪華版登場！",
      "app_name_zh": "麻將 宅神爺麻將-全新豪華版登場！",
      "developer": "Bonus Winner Online Entertainment Co. Ltd.",
      "genre": "赌场",
      "delta": 0,
      "alert": false,
      "ai_type": "社交賭場"
    },
    {
      "rank": 195,
      "app_id": "ai.projectx.clickx.gp",
      "app_name": "點消 X",
      "app_name_zh": "點消 X",
      "developer": "HeartsNet",
      "genre": "桌面和棋类",
      "delta": -20,
      "alert": false,
      "ai_type": "休閒益智"
    },
    {
      "rank": 196,
      "app_id": "com.playgendary.kickthebuddy",
      "app_name": "Kick the Buddy：有趣的動作遊戲",
      "app_name_zh": "Kick the Buddy：有趣的動作遊戲",
      "developer": "Playgendary Limited",
      "genre": "动作",
      "delta": -71,
      "alert": false,
      "ai_type": "動作競技"
    },
    {
      "rank": 197,
      "app_id": "com.FishEatFish.FeedGrow",
      "app_name": "魚吃魚：成長与進化！-Fish Eat Fish.io",
      "app_name_zh": "魚吃魚：成長与進化！-Fish Eat Fish.io",
      "developer": "MOBIBRAIN TECHNOLOGY PTE. LTD.",
      "genre": "休闲",
      "delta": -107,
      "alert": false,
      "ai_type": "休閒益智"
    },
    {
      "rank": 198,
      "app_id": "water.sort.color.puzzle.offline.games",
      "app_name": "Water Sort! Color Sort Puzzle",
      "app_name_zh": "Water Sort! Color Sort Puzzle",
      "developer": "Bobodoo Game",
      "genre": "益智",
      "delta": 0,
      "alert": false,
      "ai_type": "其他"
    },
    {
      "rank": 199,
      "app_id": "com.syubestgames.teachersimulator",
      "app_name": "我是班導",
      "app_name_zh": "我是班導",
      "developer": "Kwalee Ltd",
      "genre": "模拟",
      "delta": -34,
      "alert": false,
      "ai_type": "模擬沙盒"
    },
    {
      "rank": 200,
      "app_id": "com.zhenhunft.leshad",
      "app_name": "地獄獵手：鎮魂錄",
      "app_name_zh": "地獄獵手：鎮魂錄",
      "developer": "YTFLGames",
      "genre": "冒险",
      "delta": 0,
      "alert": false,
      "ai_type": "其他"
    }
  ],
  "type_counts_ai": {
    "其他": 32,
    "休閒益智": 82,
    "策略對戰": 23,
    "角色扮演": 21,
    "動作競技": 14,
    "社交賭場": 9,
    "模擬沙盒": 19
  },
  "type_percentages_ai": {
    "其他": 16,
    "休閒益智": 41,
    "策略對戰": 12,
    "角色扮演": 10,
    "動作競技": 7,
    "社交賭場": 4,
    "模擬沙盒": 10
  }
}